[{"id":"ffc0f7a4-8b99-445c-b3a6-5dd2226f0bd7","question":"","answer":{"answer_a":"","answer_b":"","answer_c":"","answer_d":""},"correctAnswer":"A"},{"id":"2ca03fbf-4bfc-4067-908c-41aeaa7eddce","question":"","answer":{"answer_a":"","answer_b":"","answer_c":"","answer_d":""},"correctAnswer":"A"},{"id":"4d100db4-a8ca-4ac0-a783-7b2de5ec60da","question":"","answer":{"answer_a":"","answer_b":"","answer_c":"","answer_d":""},"correctAnswer":"A"},{"id":"b82d5836-7ba6-4623-b530-24adfa3b1e4a","question":"","answer":{"answer_a":"","answer_b":"","answer_c":"","answer_d":""},"correctAnswer":"A"},{"id":"a1ac0d07-e407-4853-affa-dca264e17acf","question":"","answer":{"answer_a":"","answer_b":"","answer_c":"","answer_d":""},"correctAnswer":"A"},{"id":"5b344021-31f9-4adf-94c7-58fd029c9896","question":"dfs","answer":{"answer_a":"fds","answer_b":"sd","answer_c":"","answer_d":""},"correctAnswer":"A"},{"id":"2f5b4ca5-c7b7-453f-9b5f-da5a82a90f15","question":"adsdas","answer":{"answer_a":"aasd","answer_b":"s","answer_c":"","answer_d":""},"correctAnswer":"A"}]